problem5/problem5.v
module problem5(
    input [15:0] i_data_0,
    input [15:0] i_data_1,
    input [15:0] i_data_2,
    input [15:0] i_data_3,
    input [1:0] i_ctrl,
    input i_clk,
    output reg [15:0] o_data
);

    always @(posedge i_clk) begin
        case(i_ctrl)
            2'd0 : o_data <= i_data_0;
            2'd1 : o_data <= i_data_1;
            2'd2 : o_data <= i_data_2;
            2'd3 : o_data <= i_data_3;
            default : o_data <= 16'b0;
        endcase
    end
endmodule

problem5/problem5_tb.v
module problem_tb;
    reg [15:0] i_data_0 = 16'h0;
    reg [15:0] i_data_1 = 16'hf;
    reg [15:0] i_data_2 = 16'h5;
    reg [15:0] i_data_3 = 16'h8;
    reg [1:0] i_ctrl = 0;
    reg i_clk = 0;
    wire [15:0] o_data;

    initial begin
        $dumpfile("wave.vcd");
        $dumpvars(0, DUT);
    end

    problem5 DUT(
        .i_data_0   (i_data_0   ),
        .i_data_1   (i_data_1   ),
        .i_data_2   (i_data_2   ),
        .i_data_3   (i_data_3   ),
        .i_ctrl     (i_ctrl     ),
        .i_clk      (i_clk      ),
        .o_data     (o_data     )
    );

    always #1 begin
        i_clk <= ~i_clk;
    end

    initial begin
        #2
        i_ctrl = 2'd0;
        #2
        i_ctrl = 2'd1;
        #2
        i_ctrl = 2'd2;
        #2
        i_ctrl = 2'd3;
        #2
        i_data_0 = 16'hb;
        i_ctrl = 2'd0;
        #2
        $finish;
    end
endmodule

problem5/wave.vcd
$date
	Sat Feb 03 08:58:25 2024
$end
$version
	Icarus Verilog
$end
$timescale
	1s
$end
$scope module problem_tb $end
$scope module DUT $end
$var wire 1 ! i_clk $end
$var wire 2 " i_ctrl [1:0] $end
$var wire 16 # i_data_0 [15:0] $end
$var wire 16 $ i_data_1 [15:0] $end
$var wire 16 % i_data_2 [15:0] $end
$var wire 16 & i_data_3 [15:0] $end
$var reg 16 ' o_data [15:0] $end
$upscope $end
$upscope $end
$enddefinitions $end
$comment Show the parameter values. $end
$dumpall
$end
#0
$dumpvars
bx '
b1000 &
b101 %
b1111 $
b0 #
b0 "
0!
$end
#1
b0 '
1!
#2
0!
#3
1!
#4
0!
b1 "
#5
b1111 '
1!
#6
0!
b10 "
#7
b101 '
1!
#8
0!
b11 "
#9
b1000 '
1!
#10
0!
b0 "
b1011 #
#11
b1011 '
1!
