problem6/problem6.v
module problem6(
    input [15:0] i_data,
    input i_rst,
    input i_clk,
    output reg [2:0] o_data
);

    // 第一段階のMUX
    wire [2:0] w_0;
    function [2:0] mux_function(
        input [15:0] i_data_input
    );
    begin
        case (i_data_input[1:0])
        2'b00 : mux_function = i_data_input[4:2];
        2'b01 : mux_function = i_data_input[7:5];
        2'b10 : mux_function = i_data_input[10:8];
        2'b11 : mux_function = i_data_input[13:11];
        default : mux_function = 3'b000;
        endcase
    end
    endfunction
    assign w_0 = mux_function(i_data);


    // 第二段階のMUX
    always @(posedge i_clk) begin
        if (i_rst) begin
            o_data <= 3'b000;
        end else begin
            o_data <= w_0;
        end
    end
endmodule

problem6/problem6_tb.v
module problem6_tb;
    reg [15:0] i_data = 16'h0;
    reg i_rst = 0;
    reg i_clk = 0;
    wire [2:0] o_data;

    initial begin
        $dumpfile("wave.vcd");
        $dumpvars(0, DUT);
    end

    problem6 DUT(
        .i_data (i_data),
        .i_rst (i_rst),
        .i_clk (i_clk),
        .o_data (o_data)
    );
    
    always #1 begin
        i_clk <= ~i_clk;
    end

    initial begin
        #2
        i_data = 16'hbbb0;
        #2
        i_data = 16'hbbb1;
        #2
        i_data = 16'h3422;
        #2
        i_rst = 1;
        #2
        $finish;
    end
endmodule

problem6/wave.vcd
$date
	Sat Feb 03 10:38:47 2024
$end
$version
	Icarus Verilog
$end
$timescale
	1s
$end
$scope module problem6_tb $end
$scope module DUT $end
$var wire 1 ! i_clk $end
$var wire 16 " i_data [15:0] $end
$var wire 1 # i_rst $end
$var wire 3 $ w_0 [2:0] $end
$var reg 3 % o_data [2:0] $end
$scope function mux_function $end
$var reg 16 & i_data_input [15:0] $end
$upscope $end
$upscope $end
$upscope $end
$enddefinitions $end
$comment Show the parameter values. $end
$dumpall
$end
#0
$dumpvars
b0 &
bx %
b0 $
0#
b0 "
0!
$end
#1
b0 %
1!
#2
0!
b100 $
b1011101110110000 &
b1011101110110000 "
#3
b100 %
1!
#4
0!
b101 $
b1011101110110001 &
b1011101110110001 "
#5
b101 %
1!
#6
0!
b100 $
b11010000100010 &
b11010000100010 "
#7
b100 %
1!
#8
0!
1#
#9
b0 %
1!
